LICENSE
README.md
pyproject.toml
setup.py
src/_typepack.c
tests/test_core.py
tests/test_extensibility.py
tests/test_stream.py
tests/test_types.py
typepack/__init__.py
typepack/core.py
typepack/stream.py
typepack/types.py
typepack.egg-info/PKG-INFO
typepack.egg-info/SOURCES.txt
typepack.egg-info/dependency_links.txt
typepack.egg-info/requires.txt
typepack.egg-info/top_level.txt