Metadata-Version: 2.4
Name: typepack
Version: 0.6.1
Summary: Fast, safe binary serialization for Python supporting dataclasses, datetime, Decimal, UUID and custom types
Author: Niler Barcelos
License: MIT
Project-URL: Homepage, https://github.com/nilerbarcelos/typepack
Project-URL: Repository, https://github.com/nilerbarcelos/typepack
Keywords: serialization,binary,msgpack,pack,unpack,performance,dataclass,datetime,decimal,uuid
Classifier: Development Status :: 4 - Beta
Classifier: Intended Audience :: Developers
Classifier: License :: OSI Approved :: MIT License
Classifier: Programming Language :: Python :: 3
Classifier: Programming Language :: Python :: 3.10
Classifier: Programming Language :: Python :: 3.11
Classifier: Programming Language :: Python :: 3.12
Classifier: Programming Language :: Python :: 3.13
Classifier: Programming Language :: Python :: 3.14
Classifier: Programming Language :: C
Classifier: Topic :: Software Development :: Libraries :: Python Modules
Classifier: Topic :: Internet :: WWW/HTTP
Requires-Python: >=3.10
License-File: LICENSE
Provides-Extra: dev
Requires-Dist: pytest; extra == "dev"
Requires-Dist: build; extra == "dev"
Dynamic: license-file
